README.md
setup.cfg
setup.py
grapher/aws/__init__.py
grapher/aws/driver.py
grapher/aws/exceptions.py
grapher/aws/pricedb.py
grapher_aws.egg-info/PKG-INFO
grapher_aws.egg-info/SOURCES.txt
grapher_aws.egg-info/dependency_links.txt
grapher_aws.egg-info/entry_points.txt
grapher_aws.egg-info/requires.txt
grapher_aws.egg-info/top_level.txt